em_md/__init__.py
em_md/local_links.py
em_md-0.1.0.dist-info/METADATA
em_md-0.1.0.dist-info/WHEEL
em_md-0.1.0.dist-info/entry_points.txt
em_md-0.1.0.dist-info/top_level.txt
em_md-0.1.0.dist-info/RECORD
