Metadata-Version: 2.4
Name: em-md
Version: 0.1.0
Summary: Some markdown processing tools
Author-email: Your Name <you@example.com>
License: MIT
Requires-Python: >=3.8
